flaw2flow/__init__.py
flaw2flow/f2f.py
flaw2flow-0.1.6.dist-info/LICENSE
flaw2flow-0.1.6.dist-info/METADATA
flaw2flow-0.1.6.dist-info/WHEEL
flaw2flow-0.1.6.dist-info/top_level.txt
flaw2flow-0.1.6.dist-info/RECORD
