Metadata-Version: 2.1
Name: flaw2flow
Version: 0.1.6
Summary: flaw2flow is a Python module made to validate data in Python
Author-email: Andrea Parodi <andrea.parodi.mi@gmail.com>
License: GPL-3.0-or-later
Project-URL: Homepage, https://github.com/andreparo/flaw2flow
Project-URL: Repository, https://github.com/andreparo/flaw2flow
Project-URL: Issues, https://github.com/andreparo/flaw2flow/issues
Keywords: validation,assertion,python
Classifier: Programming Language :: Python :: 3
Classifier: Operating System :: OS Independent
Requires-Python: >=3.10
License-File: LICENSE
